{
  "region": "uk",
  "name": "英国",
  "updated_at": "2026-04-26T21:05:56.716690+00:00",
  "total": 27,
  "articles": [
    {
      "id": "2d083ebb90",
      "type": "news",
      "region": "uk",
      "source": "BBC 头条",
      "lang": "en",
      "title": "Mali defence minister killed as country hit by wave of rebel attacks",
      "summary": "A wave of coordinated attacks by jihadist militants and separatists has spread through the country.",
      "link": "https://www.bbc.com/news/articles/c5yvy7v66ndo?at_medium=RSS&at_campaign=rss",
      "image": "https://ichef.bbci.co.uk/ace/standard/240/cpsprodpb/0bb7/live/32b8b2d0-418f-11f1-ac78-2112837ce2aa.jpg",
      "categories": [
        "政治"
      ],
      "score": 70,
      "ago": "9分前",
      "pub_ts": 1777236986.0,
      "hot": false
    },
    {
      "id": "fa46e71852",
      "type": "news",
      "region": "uk",
      "source": "The Guardian",
      "lang": "en",
      "title": "Suspected gunman likely targeting Trump administration officials at White House press dinner, acting",
      "summary": "Todd Blanche says 31-year-old suspect will be charged with assault of a federal officer, discharging a firearm and attempting to kill a federal officerSuspected gunman at White House press dinner name",
      "link": "https://www.theguardian.com/us-news/live/2026/apr/26/white-house-correspondents-dinner-shooting-latest-donald-trump-suspect-washington-hilton",
      "image": "https://i.guim.co.uk/img/media/374477beef3848ed176b7fc98d1d2531e65e40be/0_0_4850_3880/master/4850.jpg?width=140&quality=85&auto=format&fit=max&s=3aa0f543a67906ce7b3cfe12d9ae68c3",
      "categories": [
        "本地"
      ],
      "score": 70,
      "ago": "26分前",
      "pub_ts": 1777235936.0,
      "hot": false
    },
    {
      "id": "a1492b3070",
      "type": "news",
      "region": "uk",
      "source": "BBC 中文",
      "lang": "zh",
      "title": "圖輯：華盛頓宴會廳驟響槍聲，晚宴現場陷入混亂",
      "summary": "當特朗普總統被緊急帶離舞台時，持槍的特勤局人員迅速湧入華盛頓一間酒店的宴會廳。",
      "link": "https://www.bbc.com/zhongwen/articles/ckgegv1p41no/trad?at_medium=RSS&at_campaign=rss",
      "image": "https://ichef.bbci.co.uk/ace/ws/240/cpsprodpb/1eb0/live/4a86fa90-4138-11f1-a08d-bd20ad597c45.jpg",
      "categories": [
        "本地"
      ],
      "score": 68,
      "ago": "14小时前",
      "pub_ts": 1777186461.0,
      "hot": false
    },
    {
      "id": "155c78156e",
      "type": "news",
      "region": "uk",
      "source": "BBC 中文",
      "lang": "zh",
      "title": "白宮記者晚宴槍擊案：31歲男子被捕、特勤人員中彈——我們還知道什麼？",
      "summary": "美國總統特朗普與第一夫人梅拉尼婭在傳出槍聲後，被迅速帶離現場。",
      "link": "https://www.bbc.com/zhongwen/articles/cx292l9pxwpo/trad?at_medium=RSS&at_campaign=rss",
      "image": "https://ichef.bbci.co.uk/ace/ws/240/cpsprodpb/5aa2/live/2c514bf0-413a-11f1-ac78-2112837ce2aa.jpg",
      "categories": [
        "本地"
      ],
      "score": 68,
      "ago": "14小时前",
      "pub_ts": 1777185481.0,
      "hot": false
    },
    {
      "id": "17f0f40be7",
      "type": "news",
      "region": "uk",
      "source": "BBC 中文",
      "lang": "zh",
      "title": "BBC記者親歷槍擊現場——當槍聲響起時，宴會廳裡的情景是怎麼樣的？",
      "summary": "BBC記者描述了當場內響起槍聲時，他和其他人如何撲倒尋找掩護的那一刻。",
      "link": "https://www.bbc.com/zhongwen/articles/c98k8y2lz03o/trad?at_medium=RSS&at_campaign=rss",
      "image": "https://ichef.bbci.co.uk/ace/ws/240/cpsprodpb/2156/live/81123170-4123-11f1-bd52-e755d604ece4.jpg",
      "categories": [
        "本地"
      ],
      "score": 68,
      "ago": "14小时前",
      "pub_ts": 1777184038.0,
      "hot": false
    },
    {
      "id": "8f874632f5",
      "type": "news",
      "region": "uk",
      "source": "BBC 中文",
      "lang": "zh",
      "title": "伊朗戰爭：特朗普取消美國特使赴巴基斯坦會談行程",
      "summary": "週六，在伊朗代表團離開伊斯蘭堡後不久，特朗普取消了美國官員原定前往巴基斯坦就伊朗戰爭進行會談的行程，稱此行「浪費了太多時間」。",
      "link": "https://www.bbc.com/zhongwen/articles/c0rxrwn4dwvo/trad?at_medium=RSS&at_campaign=rss",
      "image": "https://ichef.bbci.co.uk/ace/ws/240/cpsprodpb/dab5/live/4aaca9d0-411e-11f1-b55d-0f258dce1735.jpg",
      "categories": [
        "本地"
      ],
      "score": 68,
      "ago": "16小时前",
      "pub_ts": 1777179757.0,
      "hot": false
    },
    {
      "id": "27b2e6efaf",
      "type": "news",
      "region": "uk",
      "source": "BBC 中文",
      "lang": "zh",
      "title": "中國車企比亞迪：沒有美國市場，亦能蓬勃發展",
      "summary": "隨著燃料價格上漲，中國汽車企業比亞迪表示，正準備把握全球減少依賴化石燃料的趨勢，從中受益。",
      "link": "https://www.bbc.com/zhongwen/articles/cj404xleqlzo/trad?at_medium=RSS&at_campaign=rss",
      "image": "https://ichef.bbci.co.uk/ace/ws/240/cpsprodpb/f11a/live/c1a41c00-4121-11f1-ac78-2112837ce2aa.jpg",
      "categories": [
        "本地"
      ],
      "score": 68,
      "ago": "16小时前",
      "pub_ts": 1777177880.0,
      "hot": false
    },
    {
      "id": "dec5110e3a",
      "type": "news",
      "region": "uk",
      "source": "BBC 头条",
      "lang": "en",
      "title": "Trump and officials 'likely' targets of press dinner shooting suspect, authorities believe",
      "summary": "The suspect is expected to be charged with assault of a federal officer and using a firearm during a crime of violence, officials have said.",
      "link": "https://www.bbc.com/news/articles/c2d8dg57rzdo?at_medium=RSS&at_campaign=rss",
      "image": "https://ichef.bbci.co.uk/ace/standard/240/cpsprodpb/8b9d/live/566dacb0-41aa-11f1-ac78-2112837ce2aa.jpg",
      "categories": [
        "科技"
      ],
      "score": 65,
      "ago": "2小时前",
      "pub_ts": 1777228646.0,
      "hot": false
    },
    {
      "id": "2aad05442e",
      "type": "news",
      "region": "uk",
      "source": "BBC 头条",
      "lang": "en",
      "title": "King's US visit will go ahead as planned, Buckingham Palace says",
      "summary": "The decision was made \"after discussions on both sides of the Atlantic through the day\", the Palace says.",
      "link": "https://www.bbc.com/news/articles/cz0e0rn179eo?at_medium=RSS&at_campaign=rss",
      "image": "https://ichef.bbci.co.uk/ace/standard/240/cpsprodpb/0e0d/live/dd4fe010-414e-11f1-9d1f-0d69b57ee6a5.jpg",
      "categories": [
        "本地"
      ],
      "score": 65,
      "ago": "2小时前",
      "pub_ts": 1777228384.0,
      "hot": false
    },
    {
      "id": "b5fb6fb89f",
      "type": "news",
      "region": "uk",
      "source": "BBC 英国",
      "lang": "en",
      "title": "Man arrested for suspected arson after fire at packed LGBT+ club near Milton Keynes",
      "summary": "An eyewitness says \"thousands\" of people were evacuated from the club.",
      "link": "https://www.bbc.com/news/articles/c14548m75vlo?at_medium=RSS&at_campaign=rss",
      "image": "https://ichef.bbci.co.uk/ace/standard/240/cpsprodpb/82ce/live/c90cdb60-4178-11f1-bfbc-178a5f8f3b92.jpg",
      "categories": [
        "本地"
      ],
      "score": 65,
      "ago": "2小时前",
      "pub_ts": 1777227450.0,
      "hot": false
    },
    {
      "id": "cb21b78ffd",
      "type": "news",
      "region": "uk",
      "source": "BBC 头条",
      "lang": "en",
      "title": "Car explosion at police station treated as attempted murder",
      "summary": "The police believe the attack may have been carried out by the dissident republican group known as the New IRA.",
      "link": "https://www.bbc.com/news/articles/cp846668401o?at_medium=RSS&at_campaign=rss",
      "image": "https://ichef.bbci.co.uk/ace/standard/240/cpsprodpb/7f0b/live/32d85520-4155-11f1-ac78-2112837ce2aa.jpg",
      "categories": [
        "本地"
      ],
      "score": 65,
      "ago": "3小时前",
      "pub_ts": 1777226562.0,
      "hot": false
    },
    {
      "id": "f1ad7a2ddc",
      "type": "news",
      "region": "uk",
      "source": "The Guardian",
      "lang": "en",
      "title": "World records, Daddy Pig and a proposal: London Marathon 2026 – in pictures",
      "summary": "The London Marathon is run over a mostly flat course that starts in Blackheath and finishes on the Mall. The vast majority of the more than 59,000 participants are raising money for charity or running",
      "link": "https://www.theguardian.com/sport/gallery/2026/apr/26/world-records-daddy-pig-and-a-proposal-london-marathon-2026-in-pictures",
      "image": "https://i.guim.co.uk/img/media/5a0b6ad88f16c8b7456c4390c883a329ca6de1a6/320_55_4917_3934/master/4917.jpg?width=140&quality=85&auto=format&fit=max&s=e38107174aa36c4bc7efb9996c70e56f",
      "categories": [
        "科技"
      ],
      "score": 65,
      "ago": "3小时前",
      "pub_ts": 1777226458.0,
      "hot": false
    },
    {
      "id": "b9aecc9cec",
      "type": "news",
      "region": "uk",
      "source": "BBC 英国",
      "lang": "en",
      "title": "Starmer insists 'majority' of Labour MPs back his leadership",
      "summary": "This week has seen increasing speculation among Labour MPs about Sir Keir's judgement and leadership.",
      "link": "https://www.bbc.com/news/articles/c705228kpx9o?at_medium=RSS&at_campaign=rss",
      "image": "https://ichef.bbci.co.uk/ace/standard/240/cpsprodpb/d3bd/live/7866b810-40fc-11f1-857b-6b8d8b32a9e7.jpg",
      "categories": [
        "本地"
      ],
      "score": 65,
      "ago": "5小时前",
      "pub_ts": 1777218631.0,
      "hot": false
    },
    {
      "id": "a5ed6e3ada",
      "type": "news",
      "region": "uk",
      "source": "BBC 中文",
      "lang": "zh",
      "title": "GDP增長超預期，消費冷感揮之不去，中國經濟「溫差」何來？",
      "summary": "疫情以來，中國經濟一直困於一個公認的結構性困境：供給強於需求，外需好於內需，出口一直被視為拉動增長的最重要引擎。如今內需貢獻率驟然躍至近85%，這個結論，與近年來經濟學家的分析、外界的普遍評價，乃至普通人的體感，都不太相符。",
      "link": "https://www.bbc.com/zhongwen/articles/c2ev9nzp99yo/trad?at_medium=RSS&at_campaign=rss",
      "image": "https://ichef.bbci.co.uk/ace/ws/240/cpsprodpb/aa80/live/74f8f0d0-3ef4-11f1-95e9-c9f2031e3375.jpg",
      "categories": [
        "本地"
      ],
      "score": 63,
      "ago": "2天前",
      "pub_ts": 1776990399.0,
      "hot": false
    },
    {
      "id": "8da9ef89ff",
      "type": "news",
      "region": "uk",
      "source": "BBC 英国",
      "lang": "en",
      "title": "Woman released on bail after fatal house fire",
      "summary": "Police said two boys, aged one and three, died at the scene. A woman in her 30s was arrested.",
      "link": "https://www.bbc.com/news/articles/cwyxy7jy5w6o?at_medium=RSS&at_campaign=rss",
      "image": "https://ichef.bbci.co.uk/ace/standard/240/cpsprodpb/73a6/live/f8a62660-4155-11f1-9d1f-0d69b57ee6a5.jpg",
      "categories": [
        "科技"
      ],
      "score": 60,
      "ago": "6小时前",
      "pub_ts": 1777215663.0,
      "hot": false
    },
    {
      "id": "aea986bed6",
      "type": "news",
      "region": "uk",
      "source": "BBC 头条",
      "lang": "en",
      "title": "Suspected gunman identified as 31-year-old Californian",
      "summary": "The man arrested at the event attended by President Trump has been named in US media as Cole Tomas Allen from California.",
      "link": "https://www.bbc.com/news/articles/cr717nglye0o?at_medium=RSS&at_campaign=rss",
      "image": "https://ichef.bbci.co.uk/ace/standard/240/cpsprodpb/e8d7/live/e736b710-415e-11f1-bd52-e755d604ece4.jpg",
      "categories": [
        "本地"
      ],
      "score": 60,
      "ago": "7小时前",
      "pub_ts": 1777211989.0,
      "hot": false
    },
    {
      "id": "d00dd636bc",
      "type": "news",
      "region": "uk",
      "source": "BBC 头条",
      "lang": "en",
      "title": "Higher prices could last for eight months after Iran war, minister says",
      "summary": "Officials are monitoring stock levels and planning for any potential disruptions to the supply chain.",
      "link": "https://www.bbc.com/news/articles/cm29m98md2do?at_medium=RSS&at_campaign=rss",
      "image": "https://ichef.bbci.co.uk/ace/standard/240/cpsprodpb/e770/live/74d53e30-414f-11f1-9d1f-0d69b57ee6a5.jpg",
      "categories": [
        "政治",
        "科技"
      ],
      "score": 60,
      "ago": "7小时前",
      "pub_ts": 1777211934.0,
      "hot": false
    },
    {
      "id": "ef4344f6d2",
      "type": "news",
      "region": "uk",
      "source": "The Guardian",
      "lang": "en",
      "title": "Pope Leo has stirred awake a progressive Christianity. It can rise again | Bill McKibben",
      "summary": "With his stand against Trump, the pope has shown the far right doesn’t have a monopoly on Christianity. If people of good faith push hard, the future could be redefinedIn the same way that America’s s",
      "link": "https://www.theguardian.com/us-news/ng-interactive/2026/apr/26/pope-leo-trump-hegseth-christianity",
      "image": "https://i.guim.co.uk/img/media/0b6805d43a1a2c82ef1a2e334f0c0c5b086a9f67/0_0_1904_1523/master/1904.jpg?width=140&quality=85&auto=format&fit=max&s=909012d60a4ec874d097e513d3e36289",
      "categories": [
        "科技"
      ],
      "score": 60,
      "ago": "8小时前",
      "pub_ts": 1777208416.0,
      "hot": false
    },
    {
      "id": "a37062e418",
      "type": "news",
      "region": "uk",
      "source": "The Guardian",
      "lang": "en",
      "title": "The surprising boom in blouge wine: ‘It’s for 5pm, in the sun’",
      "summary": "Literally a mix of white (blanc) and red (rouge) grapes, the light, fresh tipple is popping up in bars around the world. Move over rosé and orange wine ...Twenty years ago, a winery could do well sell",
      "link": "https://www.theguardian.com/food/2026/apr/26/blouge-natural-wine-trend",
      "image": "https://i.guim.co.uk/img/media/13d102d5ceb6d82ce7eb0394b8f32da44d6f3af5/0_498_4000_3200/master/4000.jpg?width=140&quality=85&auto=format&fit=max&s=6bc82f61f9512c05526bc608d9fac20d",
      "categories": [
        "本地"
      ],
      "score": 60,
      "ago": "8小时前",
      "pub_ts": 1777208416.0,
      "hot": false
    },
    {
      "id": "f4b4bd8b3b",
      "type": "news",
      "region": "uk",
      "source": "BBC 头条",
      "lang": "en",
      "title": "Sabastian Sawe breaks two-hour barrier to make history at London Marathon",
      "summary": "Sabastian Sawe makes history at the London Marathon as the first person to run a sub-two-hour marathon in a competitive race.",
      "link": "https://www.bbc.com/sport/athletics/articles/crm1m7e0zwzo?at_medium=RSS&at_campaign=rss",
      "image": "https://ichef.bbci.co.uk/ace/standard/240/cpsprodpb/c55d/live/abbc5210-4179-11f1-bd52-e755d604ece4.jpg",
      "categories": [
        "本地"
      ],
      "score": 60,
      "ago": "8小时前",
      "pub_ts": 1777207189.0,
      "hot": false
    },
    {
      "id": "bb4711f183",
      "type": "news",
      "region": "uk",
      "source": "BBC 英国",
      "lang": "en",
      "title": "Sawe smashes two-hour mark to 'move goalposts for marathon running'",
      "summary": "Sabastian Sawe makes history at the London Marathon as the first person to run a sub-two-hour marathon in a competitive race.",
      "link": "https://www.bbc.com/sport/athletics/articles/crm1m7e0zwzo?at_medium=RSS&at_campaign=rss",
      "image": "https://ichef.bbci.co.uk/ace/standard/240/cpsprodpb/b363/live/5c67a4a0-4163-11f1-8a25-27287a9e092d.jpg",
      "categories": [
        "本地"
      ],
      "score": 60,
      "ago": "8小时前",
      "pub_ts": 1777207189.0,
      "hot": false
    },
    {
      "id": "dae64598ac",
      "type": "news",
      "region": "uk",
      "source": "The Guardian",
      "lang": "en",
      "title": "Dining across the divide: ‘In France we’d be at each other’s throats, but in the UK you say the most",
      "summary": "One moved to the UK 20 years ago. The other is considering a vote for Restore Britain. Could they agree on national symbols and Brexit?• Want to meet someone from across the divide? Click here to find",
      "link": "https://www.theguardian.com/lifeandstyle/2026/apr/26/dining-across-the-divide-in-france-wed-be-at-each-others-throats-but-in-the-uk-you-say-the-most-horrible-things-smiling",
      "image": "https://i.guim.co.uk/img/media/569ac8c9aeaba97c3016fcbd14ea2cc5adb08016/733_43_5050_4040/master/5050.jpg?width=140&quality=85&auto=format&fit=max&s=4820d4541b278476b862d52e76c5e894",
      "categories": [
        "科技"
      ],
      "score": 60,
      "ago": "10小时前",
      "pub_ts": 1777201213.0,
      "hot": false
    },
    {
      "id": "dd80a4c85d",
      "type": "news",
      "region": "uk",
      "source": "The Guardian",
      "lang": "en",
      "title": "I yearned to be a mother. Why did I feel nothing when my daughter was finally born?",
      "summary": "I had presumed I would love her instantly – but a traumatic birth led to devastating numbnessIt wasn’t supposed to be like this. I was waiting for an overwhelming rush of love, but when I looked at my",
      "link": "https://www.theguardian.com/lifeandstyle/2026/apr/26/i-yearned-to-be-a-mother-why-did-i-feel-nothing-when-my-daughter-was-finally-born",
      "image": "https://i.guim.co.uk/img/media/e5d457c26c068558c3fe86d8357616a1768899f4/0_2004_5920_4734/master/5920.jpg?width=140&quality=85&auto=format&fit=max&s=2ac83d590d1588477a90012e5861a47f",
      "categories": [
        "科技"
      ],
      "score": 60,
      "ago": "10小时前",
      "pub_ts": 1777201212.0,
      "hot": false
    },
    {
      "id": "b0f3eaca54",
      "type": "news",
      "region": "uk",
      "source": "The Guardian",
      "lang": "en",
      "title": "I’ve covered Trump for a decade. At the White House correspondents’ dinner, darkness came viscerally",
      "summary": "Men in tuxedos and women in dresses dove under tables, like a scene from a dozen Hollywood movies, but now it was happening to meWhite House correspondents’ dinner shooting – latest updatesShocking. U",
      "link": "https://www.theguardian.com/us-news/2026/apr/26/white-house-correspondents-dinner-shooting-covering-trump",
      "image": "https://i.guim.co.uk/img/media/859773f8276596e2d8f92a327f2156019e8d29c9/468_0_4680_3744/master/4680.jpg?width=140&quality=85&auto=format&fit=max&s=acee8e84619a2c969cc9e25cd0477b43",
      "categories": [
        "本地"
      ],
      "score": 60,
      "ago": "11小时前",
      "pub_ts": 1777197611.0,
      "hot": false
    },
    {
      "id": "aba1e115e7",
      "type": "news",
      "region": "uk",
      "source": "BBC 头条",
      "lang": "en",
      "title": "Watch: How gunfire sparked chaos at Trump press dinner",
      "summary": "President Trump and Vice-President Vance were rushed off the stage, after gunshots were heard at the event at the Washington Hilton hotel.",
      "link": "https://www.bbc.com/news/videos/cgqkq18qqeeo?at_medium=RSS&at_campaign=rss",
      "image": "https://ichef.bbci.co.uk/ace/standard/240/cpsprodpb/c223/live/c8629b30-4184-11f1-b55d-0f258dce1735.jpg",
      "categories": [
        "本地"
      ],
      "score": 60,
      "ago": "11小时前",
      "pub_ts": 1777196622.0,
      "hot": false
    },
    {
      "id": "c6ce081075",
      "type": "news",
      "region": "uk",
      "source": "The Guardian",
      "lang": "en",
      "title": "‘We asked Billy Connolly to do 15 minutes. He said “I’ll do as long as I want”’: the sweary, shambol",
      "summary": "Today it is a fundraising juggernaut, but when it was born 40 years ago this month, things were very different. Lenny Henry, Richard Curtis and more explain how they got the gang together for a good c",
      "link": "https://www.theguardian.com/tv-and-radio/2026/apr/26/comic-relief-40-years-british-comedy",
      "image": "https://i.guim.co.uk/img/media/bd824373a100838ebe38ddb7f921ed4a74bc9f85/75_21_2777_2220/master/2777.jpg?width=140&quality=85&auto=format&fit=max&s=81f80910fdaa367e94f84b5b15e3517b",
      "categories": [
        "科技"
      ],
      "score": 60,
      "ago": "12小时前",
      "pub_ts": 1777194010.0,
      "hot": false
    },
    {
      "id": "cf24070c08",
      "type": "news",
      "region": "uk",
      "source": "BBC 英国",
      "lang": "en",
      "title": "The crime that never happened - and sparked a rage bait frenzy",
      "summary": "Misinformation about an alleged rape in Epsom became a real-world storm, but we've been here before.",
      "link": "https://www.bbc.com/news/articles/c9370jqxy18o?at_medium=RSS&at_campaign=rss",
      "image": "https://ichef.bbci.co.uk/ace/standard/240/cpsprodpb/b191/live/d5d85a90-416e-11f1-ac78-2112837ce2aa.jpg",
      "categories": [
        "天气",
        "科技"
      ],
      "score": 60,
      "ago": "22小时前",
      "pub_ts": 1777158206.0,
      "hot": false
    }
  ]
}