{
  "region": "uk",
  "name": "英国",
  "updated_at": "2026-03-25T05:40:17.020357+00:00",
  "total": 29,
  "articles": [
    {
      "id": "a1bc4dc9bb",
      "type": "news",
      "region": "uk",
      "source": "BBC 中文",
      "lang": "zh",
      "title": "「保姆車」和「流量明星」：中國影視監管當局為何要打擊「撕番位」？",
      "summary": "一名不願透露姓名的中國影視產業工作者向BBC中文表示，「番位之爭」從過去不可⾔說的默契，演化到具有合約效益的商業權益；目前已不限於演員，更包括導演､ 編劇､ 攝影等核⼼⼯種｡",
      "link": "https://www.bbc.com/zhongwen/articles/c8r4lzp4m2do/trad?at_medium=RSS&at_campaign=rss",
      "image": "https://ichef.bbci.co.uk/ace/ws/240/cpsprodpb/8d3b/live/ee03e000-2759-11f1-a797-4bd7869bf0d1.jpg",
      "categories": [
        "华人"
      ],
      "score": 85,
      "ago": "5小时前",
      "pub_ts": 1774397823.0,
      "hot": false
    },
    {
      "id": "b8786ca6e6",
      "type": "news",
      "region": "uk",
      "source": "BBC 中文",
      "lang": "zh",
      "title": "分析：美伊談判小窗口已開，但迅速結束戰爭仍不太可能",
      "summary": "美國總統特朗普表示，美方已經在與伊朗的一位「最高層人士」接觸，但德黑蘭否認任何談判已經開始。",
      "link": "https://www.bbc.com/zhongwen/articles/c62j784n11zo/trad?at_medium=RSS&at_campaign=rss",
      "image": "https://ichef.bbci.co.uk/ace/ws/240/cpsprodpb/5e3a/live/a33b24e0-27a7-11f1-a8d3-5d54fcb90a80.jpg",
      "categories": [
        "本地"
      ],
      "score": 78,
      "ago": "1小时前",
      "pub_ts": 1774411183.0,
      "hot": false
    },
    {
      "id": "fb76e575a8",
      "type": "news",
      "region": "uk",
      "source": "BBC 中文",
      "lang": "zh",
      "title": "別一味計算卡路里了，吃得聰明一些更有用",
      "summary": "你吃飯的時間、你吃得多快，甚至你咀嚼的次數，都會影響你從食物中吸收多少卡路里。",
      "link": "https://www.bbc.com/zhongwen/articles/cde570879eyo/trad?at_medium=RSS&at_campaign=rss",
      "image": "https://ichef.bbci.co.uk/ace/ws/240/cpsprodpb/94ea/live/77a942b0-2759-11f1-a797-4bd7869bf0d1.jpg",
      "categories": [
        "本地"
      ],
      "score": 73,
      "ago": "5小时前",
      "pub_ts": 1774397884.0,
      "hot": false
    },
    {
      "id": "5df4c9e7d5",
      "type": "news",
      "region": "uk",
      "source": "The Guardian",
      "lang": "en",
      "title": "Middle East crisis live: Iran launches strikes on US bases in Gulf; oil prices drop after Trump ‘pea",
      "summary": "Iran Guards said they fired missiles at Israel and US forces in bases in Kuwait, Jordan and Bahrain; crude oil prices fall sharply in early tradingTrump’s rehashed 15-point Iran plan unlikely to appea",
      "link": "https://www.theguardian.com/world/live/2026/mar/25/middle-east-crisis-live-iran-war-oil-prices-more-us-troops-reportedly-deployed-donald-trump-attacks-on-lebanon",
      "image": "https://i.guim.co.uk/img/media/55af21063b71a2a1b1e15c3c89c57f1f81fed455/578_262_3053_2442/master/3053.jpg?width=140&quality=85&auto=format&fit=max&s=7b08aad3acf73f44bf69c27b5090cb4d",
      "categories": [
        "天气",
        "科技"
      ],
      "score": 70,
      "ago": "31分前",
      "pub_ts": 1774415330.0,
      "hot": false
    },
    {
      "id": "3e6222e762",
      "type": "news",
      "region": "uk",
      "source": "The Guardian",
      "lang": "en",
      "title": "‘Truly vile’: the UK’s 25 best (and worst) novelty hot cross buns – tested!",
      "summary": "Can you beat a traditional spiced yeast bun at Easter? There’s only one way to find out. Bring on the rhubarb and custard version, the red velvet, the chocolate and fudge, the tiramisu …Hot cross buns",
      "link": "https://www.theguardian.com/food/2026/mar/25/25-best-worst-novelty-hot-cross-buns-tested-uk",
      "image": "https://i.guim.co.uk/img/media/b5a8195340841d5e5f5fee709e6b7337944c15be/150_0_9375_7500/master/9375.jpg?width=140&quality=85&auto=format&fit=max&s=e09bb2d896794ed1a5aa6b8ce8a4af7e",
      "categories": [
        "本地"
      ],
      "score": 70,
      "ago": "40分前",
      "pub_ts": 1774414802.0,
      "hot": false
    },
    {
      "id": "2add7eecb7",
      "type": "news",
      "region": "uk",
      "source": "BBC 英国",
      "lang": "en",
      "title": "Adolescence star Owen Cooper takes two RTS Awards",
      "summary": "Owen Cooper wins double for his standout performance in the Netflix drama show.",
      "link": "https://www.bbc.com/news/articles/c5yj46r2jqno?at_medium=RSS&at_campaign=rss",
      "image": "https://ichef.bbci.co.uk/ace/standard/240/cpsprodpb/c3db/live/bac36f70-27ff-11f1-9e21-711dd35e44a9.jpg",
      "categories": [
        "本地"
      ],
      "score": 70,
      "ago": "1小时前",
      "pub_ts": 1774411703.0,
      "hot": false
    },
    {
      "id": "7004d21154",
      "type": "news",
      "region": "uk",
      "source": "BBC 中文",
      "lang": "zh",
      "title": "香港政府僱員袁松彪否認曾下令監視在英異見人士",
      "summary": "前香港警務人員袁松彪表示，他並未在倫敦組織「影子執法」行動。",
      "link": "https://www.bbc.com/zhongwen/articles/cvg04y3d6v6o/trad?at_medium=RSS&at_campaign=rss",
      "image": "https://ichef.bbci.co.uk/ace/ws/240/cpsprodpb/87ee/live/4c311d50-26fb-11f1-8882-999738731502.jpg",
      "categories": [
        "政治"
      ],
      "score": 68,
      "ago": "22小时前",
      "pub_ts": 1774337608.0,
      "hot": false
    },
    {
      "id": "1f546310ba",
      "type": "news",
      "region": "uk",
      "source": "BBC 中文",
      "lang": "zh",
      "title": "從藥劑師到思鄉博主：看伊朗戰爭的平民代價",
      "summary": "隨著美國和以色列對伊朗的戰爭持續，平民死傷人數正急劇攀升。",
      "link": "https://www.bbc.com/zhongwen/articles/czjw78z3mpvo/trad?at_medium=RSS&at_campaign=rss",
      "image": "https://ichef.bbci.co.uk/ace/ws/240/cpsprodpb/d3e0/live/5181ce60-26df-11f1-934f-036468834728.jpg",
      "categories": [
        "本地"
      ],
      "score": 68,
      "ago": "23小时前",
      "pub_ts": 1774331746.0,
      "hot": false
    },
    {
      "id": "8131570c6a",
      "type": "news",
      "region": "uk",
      "source": "BBC 英国",
      "lang": "en",
      "title": "'I hugged armed man to stop him bombing hospital'",
      "summary": "Nathan Newby, who used kindness to persuade the \"lone-wolf terrorist\" to abandon his plan, is being awarded the George Medal.",
      "link": "https://www.bbc.com/news/articles/c9q58xq9lxzo?at_medium=RSS&at_campaign=rss",
      "image": "https://ichef.bbci.co.uk/ace/standard/240/cpsprodpb/f496/live/2165df10-2774-11f1-82f7-f757ccb9d4bd.jpg",
      "categories": [
        "本地"
      ],
      "score": 65,
      "ago": "3小时前",
      "pub_ts": 1774404025.0,
      "hot": false
    },
    {
      "id": "4f7027efe2",
      "type": "news",
      "region": "uk",
      "source": "BBC 头条",
      "lang": "en",
      "title": "NHS dentistry is rotting. Will the plan to fix it work?",
      "summary": "As patients struggle to find NHS dentists, Labour has a plan but not everybody is convinced it will work",
      "link": "https://www.bbc.com/news/articles/cr41lg6ddelo?at_medium=RSS&at_campaign=rss",
      "image": "https://ichef.bbci.co.uk/ace/standard/240/cpsprodpb/fc52/live/28ea5050-2769-11f1-934f-036468834728.jpg",
      "categories": [
        "本地"
      ],
      "score": 65,
      "ago": "4小时前",
      "pub_ts": 1774402000.0,
      "hot": false
    },
    {
      "id": "e4a90eb71d",
      "type": "news",
      "region": "uk",
      "source": "BBC 头条",
      "lang": "en",
      "title": "'Wildy unaffordable': The harsh reality of shared ownership",
      "summary": "For many, the promise of getting a foot on the property ladder has turned into a nightmare.",
      "link": "https://www.bbc.com/news/articles/cm25e8k2je1o?at_medium=RSS&at_campaign=rss",
      "image": "https://ichef.bbci.co.uk/ace/standard/240/cpsprodpb/7778/live/132df010-27a9-11f1-9089-39d9725da55d.jpg",
      "categories": [
        "本地"
      ],
      "score": 65,
      "ago": "4小时前",
      "pub_ts": 1774401786.0,
      "hot": false
    },
    {
      "id": "36a397e530",
      "type": "news",
      "region": "uk",
      "source": "BBC 头条",
      "lang": "en",
      "title": "NHS waited two days before raising alarm about meningitis outbreak",
      "summary": "Experts say the wait was indefensible and possibly delayed identification of the outbreak.",
      "link": "https://www.bbc.com/news/articles/cp8dnxln3y5o?at_medium=RSS&at_campaign=rss",
      "image": "https://ichef.bbci.co.uk/ace/standard/240/cpsprodpb/f869/live/3e6a6ad0-27ed-11f1-b297-95b0a0a8331e.jpg",
      "categories": [
        "科技"
      ],
      "score": 65,
      "ago": "5小时前",
      "pub_ts": 1774398375.0,
      "hot": false
    },
    {
      "id": "c1d8288b09",
      "type": "news",
      "region": "uk",
      "source": "The Guardian",
      "lang": "en",
      "title": "Schiaparelli review – it’s cocktail o’clock with fashion’s surreal goddess who out-lobstered Dalí an",
      "summary": "V&A South Kensington, LondonThe Italian designer loved to shock and this dazzling show is like sashaying through a party in 1930s Paris with Schiap and her darling friends Cocteau and DalíNaked mermai",
      "link": "https://www.theguardian.com/fashion/2026/mar/25/schiaparelli-fashion-becomes-art-dali-cocteau-surreal-v-and-a",
      "image": "https://i.guim.co.uk/img/media/e0d6855a93bb16b6b4693a88c3b9b568d392d955/833_156_2781_2225/master/2781.jpg?width=140&quality=85&auto=format&fit=max&s=692b90515df8f106e9376300fc952fc1",
      "categories": [
        "科技"
      ],
      "score": 65,
      "ago": "5小时前",
      "pub_ts": 1774396912.0,
      "hot": false
    },
    {
      "id": "a0793da629",
      "type": "news",
      "region": "uk",
      "source": "BBC 头条",
      "lang": "en",
      "title": "Oil at $150 would trigger global recession, says boss of financial giant BlackRock",
      "summary": "Larry Fink says if oil prices stay high for a sustained period it will have \"profound implications\" for the world economy.",
      "link": "https://www.bbc.com/news/articles/c9wqrdkx8ppo?at_medium=RSS&at_campaign=rss",
      "image": "https://ichef.bbci.co.uk/ace/standard/240/cpsprodpb/30fd/live/65c23d50-27ad-11f1-a79a-77e93010d956.jpg",
      "categories": [
        "经济",
        "科技"
      ],
      "score": 65,
      "ago": "5小时前",
      "pub_ts": 1774396820.0,
      "hot": false
    },
    {
      "id": "24385b9e1e",
      "type": "news",
      "region": "uk",
      "source": "BBC 中文",
      "lang": "zh",
      "title": "分析：戰爭持續越久，美國和伊朗就會更加陷入欲罷不能的境地",
      "summary": "特朗普的選項越來越少。進一步升級可能成為無止境的破壞循環，卻缺乏明確戰略利益，使剩下的只會是最極端的方案。伊朗局勢同樣艱難。該國在衝突前就已面臨經濟壓力和廣泛民怨，若後退將顯得軟弱。",
      "link": "https://www.bbc.com/zhongwen/articles/cy01g4kpkk7o/trad?at_medium=RSS&at_campaign=rss",
      "image": "https://ichef.bbci.co.uk/ace/ws/240/cpsprodpb/ff5a/live/bde680f0-2608-11f1-934f-036468834728.jpg",
      "categories": [
        "本地"
      ],
      "score": 63,
      "ago": "昨日",
      "pub_ts": 1774326115.0,
      "hot": false
    },
    {
      "id": "75da700dbd",
      "type": "news",
      "region": "uk",
      "source": "BBC 中文",
      "lang": "zh",
      "title": "當AI智能體開始上崗：2026年春天裡，三個中國人的興奮與恐懼",
      "summary": "一個是極客，一個是創業者，一個是程序員。他們的情緒各不相同，興奮、恐懼，或者兩者同時發生。他們站的位置不同，聽到的轟鳴聲卻來自同一個方向。",
      "link": "https://www.bbc.com/zhongwen/articles/crm8mmg0y3eo/trad?at_medium=RSS&at_campaign=rss",
      "image": "https://ichef.bbci.co.uk/ace/ws/240/cpsprodpb/3e3a/live/805313b0-2375-11f1-8f74-5f782ec9b448.jpg",
      "categories": [
        "科技"
      ],
      "score": 63,
      "ago": "昨日",
      "pub_ts": 1774320314.0,
      "hot": false
    },
    {
      "id": "11495d76b5",
      "type": "news",
      "region": "uk",
      "source": "BBC 中文",
      "lang": "zh",
      "title": "為何海灣國家尚未報復伊朗？",
      "summary": "專家表示，海灣國家不願直接捲入戰爭，但不太可能接受無限期地遭受攻擊。",
      "link": "https://www.bbc.com/zhongwen/articles/c0lep1nexx3o/trad?at_medium=RSS&at_campaign=rss",
      "image": "https://ichef.bbci.co.uk/ace/ws/240/cpsprodpb/a4e5/live/72bb0760-268d-11f1-82d0-fd391f4a7261.jpg",
      "categories": [
        "本地"
      ],
      "score": 63,
      "ago": "昨日",
      "pub_ts": 1774253491.0,
      "hot": false
    },
    {
      "id": "9ba33c76e5",
      "type": "news",
      "region": "uk",
      "source": "BBC 头条",
      "lang": "en",
      "title": "Meta told to pay $375m for misleading users over child safety",
      "summary": "The owner of Instagram, Facebook and WhatsApp has been found liable by a court in New Mexico.",
      "link": "https://www.bbc.com/news/articles/cql75dn07n2o?at_medium=RSS&at_campaign=rss",
      "image": "https://ichef.bbci.co.uk/ace/standard/240/cpsprodpb/438d/live/50569720-27d7-11f1-94c7-894c2c5c70c3.jpg",
      "categories": [
        "本地"
      ],
      "score": 60,
      "ago": "6小时前",
      "pub_ts": 1774394215.0,
      "hot": false
    },
    {
      "id": "31d6accc36",
      "type": "news",
      "region": "uk",
      "source": "The Guardian",
      "lang": "en",
      "title": "Power: The Downfall of Huw Edwards review – Martin Clunes is sickening",
      "summary": "The actor is horribly convincing in this ripped-from-the-headlines drama about the newsreader’s grooming scandal. You might not even be able to stomach itWhen future generations look back at all the t",
      "link": "https://www.theguardian.com/tv-and-radio/2026/mar/24/power-the-downfall-of-huw-edwards-review-martin-clunes-is-sickening",
      "image": "https://i.guim.co.uk/img/media/2e751e868172dcb63ef4cc6ae4f88088b5ea2dd0/9_451_3818_3053/master/3818.jpg?width=140&quality=85&auto=format&fit=max&s=8a43b3ed3dcb7e7e06706d67f633ce1f",
      "categories": [
        "本地"
      ],
      "score": 60,
      "ago": "6小时前",
      "pub_ts": 1774392650.0,
      "hot": false
    },
    {
      "id": "ff341d6356",
      "type": "news",
      "region": "uk",
      "source": "BBC 头条",
      "lang": "en",
      "title": "Social media bans and digital curfews to be trialled on UK teenagers",
      "summary": "The government will interview the young people and their parents before and after they try the limits to assess their impact.",
      "link": "https://www.bbc.com/news/articles/cn89g3ngkyzo?at_medium=RSS&at_campaign=rss",
      "image": "https://ichef.bbci.co.uk/ace/standard/240/cpsprodpb/c3d2/live/8bba8cc0-27a2-11f1-ac4d-5987f4dee3ad.jpg",
      "categories": [
        "政治",
        "科技"
      ],
      "score": 60,
      "ago": "7小时前",
      "pub_ts": 1774391851.0,
      "hot": false
    },
    {
      "id": "47de12be82",
      "type": "news",
      "region": "uk",
      "source": "BBC 英国",
      "lang": "en",
      "title": "Families urged not to cuddle lambs after infection outbreak left dozens sick",
      "summary": "Health officials say it is vital to remember that young farm animals can carry germs that cause illness.",
      "link": "https://www.bbc.com/news/articles/cj60kn2w32ko?at_medium=RSS&at_campaign=rss",
      "image": "https://ichef.bbci.co.uk/ace/standard/240/cpsprodpb/419e/live/11ef1740-26d4-11f1-a79a-77e93010d956.png",
      "categories": [
        "本地"
      ],
      "score": 60,
      "ago": "7小时前",
      "pub_ts": 1774391645.0,
      "hot": false
    },
    {
      "id": "32327dacce",
      "type": "news",
      "region": "uk",
      "source": "BBC 头条",
      "lang": "en",
      "title": "'It wasn't meant to end like this' - Salah exit tough but inevitable",
      "summary": "Less than a year ago, Mohamed Salah was sitting on a throne inside Anfield after renewing his contract - so why is he leaving?",
      "link": "https://www.bbc.com/sport/football/articles/cq8wqq8neg1o?at_medium=RSS&at_campaign=rss",
      "image": "https://ichef.bbci.co.uk/ace/standard/240/cpsprodpb/95a5/live/3c1db0f0-27c7-11f1-ac18-87607d10fbfe.jpg",
      "categories": [
        "本地"
      ],
      "score": 60,
      "ago": "7小时前",
      "pub_ts": 1774391591.0,
      "hot": false
    },
    {
      "id": "932c7e34aa",
      "type": "news",
      "region": "uk",
      "source": "BBC 英国",
      "lang": "en",
      "title": "Salah to leave Liverpool at end of season",
      "summary": "The Egypt forward says Liverpool fans \"gave me the best time of my life\" and \"stood by me in the toughest times\".",
      "link": "https://www.bbc.com/sport/football/articles/c0e7ww12w2qo?at_medium=RSS&at_campaign=rss",
      "image": "https://ichef.bbci.co.uk/ace/standard/240/cpsprodpb/f604/live/e9c4cdc0-27bc-11f1-a79a-77e93010d956.jpg",
      "categories": [
        "本地"
      ],
      "score": 60,
      "ago": "9小时前",
      "pub_ts": 1774384463.0,
      "hot": false
    },
    {
      "id": "576139f309",
      "type": "news",
      "region": "uk",
      "source": "The Guardian",
      "lang": "en",
      "title": "UK offers to host international summit on reopening strait of Hormuz",
      "summary": "Defence chiefs have been discussing how to unblock the conduit for about a fifth of the world’s oil suppliesThe UK has offered to host an international security summit to draw up a “viable, collective",
      "link": "https://www.theguardian.com/world/2026/mar/24/uk-offers-to-host-international-security-summit-on-reopening-strait-of-hormuz",
      "image": "https://i.guim.co.uk/img/media/925f0eb4035965a937744c23d22a7e807e88a573/137_0_1320_1056/master/1320.jpg?width=140&quality=85&auto=format&fit=max&s=a6707b2577e9d4070019bfb3f157c46b",
      "categories": [
        "科技"
      ],
      "score": 60,
      "ago": "10小时前",
      "pub_ts": 1774379932.0,
      "hot": false
    },
    {
      "id": "184905b1e2",
      "type": "news",
      "region": "uk",
      "source": "BBC 头条",
      "lang": "en",
      "title": "Lyse Doucet: Small window open for US-Iran talks, but swift end to war still unlikely",
      "summary": "President Trump says the US is already dealing with a \"top person\" in Iran, but Tehran denies that any talks have begun.",
      "link": "https://www.bbc.com/news/articles/c895xljyzewo?at_medium=RSS&at_campaign=rss",
      "image": "https://ichef.bbci.co.uk/ace/standard/240/cpsprodpb/5e3a/live/a33b24e0-27a7-11f1-a8d3-5d54fcb90a80.jpg",
      "categories": [
        "本地"
      ],
      "score": 60,
      "ago": "11小时前",
      "pub_ts": 1774375444.0,
      "hot": false
    },
    {
      "id": "52bd0feae5",
      "type": "news",
      "region": "uk",
      "source": "The Guardian",
      "lang": "en",
      "title": "Reeves slips into yoga voice to try to soothe fears over costs of Trump’s war | John Crace",
      "summary": "The chancellor was meant to set out her contingency plans but it was an announcement without any announcements in itYou have to feel a bit sorry for the chancellor. Roughly four weeks ago, Rachel Reev",
      "link": "https://www.theguardian.com/politics/2026/mar/24/rachel-reeves-yoga-voice-war-commons-sketch",
      "image": "https://i.guim.co.uk/img/media/98e0571ac76f20cc55d846c0ccb31691c1bb60aa/1376_0_6880_5504/master/6880.jpg?width=140&quality=85&auto=format&fit=max&s=4dbf9621b37e0708c728009ff147731f",
      "categories": [
        "本地"
      ],
      "score": 60,
      "ago": "12小时前",
      "pub_ts": 1774371932.0,
      "hot": false
    },
    {
      "id": "a15b92fa0d",
      "type": "news",
      "region": "uk",
      "source": "The Guardian",
      "lang": "en",
      "title": "I lost every good acting job to Riz Ahmed – annoyingly, his James Bond comedy is a jaw-dropping hoot",
      "summary": "Ahmed superbly tackles race and identity in his hilarious new show Bait, proving the British-Asian actor truly is the best of this country. I’m happy for him, I swear!Conflicted feelings for me this w",
      "link": "https://www.theguardian.com/tv-and-radio/2026/mar/24/bait-riz-ahmed-british-asian-actors-race",
      "image": "https://i.guim.co.uk/img/media/a7565ea8a1dfc7096e7e3c7abf74fb50771c68f7/330_78_2015_1612/master/2015.jpg?width=140&quality=85&auto=format&fit=max&s=de69972754e3e84c752931d1593ebdde",
      "categories": [
        "科技"
      ],
      "score": 60,
      "ago": "12小时前",
      "pub_ts": 1774370891.0,
      "hot": false
    },
    {
      "id": "dbc9c2c4af",
      "type": "news",
      "region": "uk",
      "source": "The Guardian",
      "lang": "en",
      "title": "How I Shop with Henry Holland: ‘I have a bit of a shoe problem’",
      "summary": "Always wondered what everyday stuff celebrities buy, where they shop for food and the basic they scrimp on? Henry Holland talks Labubus, vintage Prada and swapping Calvins for Skims with the Filter• D",
      "link": "https://www.theguardian.com/thefilter/2026/mar/24/how-i-shop-with-henry-holland",
      "image": "https://i.guim.co.uk/img/media/1006dfd64f9fd78b11db3639966e4eb464e70b77/0_0_2480_1984/master/2480.png?width=140&quality=85&auto=format&fit=max&s=87b47868192cb908e0d8e3df3f44b90b",
      "categories": [
        "本地"
      ],
      "score": 60,
      "ago": "14小时前",
      "pub_ts": 1774364440.0,
      "hot": false
    },
    {
      "id": "d19a0a3a1d",
      "type": "news",
      "region": "uk",
      "source": "BBC 英国",
      "lang": "en",
      "title": "Transgender girls told to leave Girlguiding groups by September",
      "summary": "It follows an announcement in December that transgender members would be banned from joining.",
      "link": "https://www.bbc.com/news/articles/cx2rn250ddjo?at_medium=RSS&at_campaign=rss",
      "image": "https://ichef.bbci.co.uk/ace/standard/240/cpsprodpb/ad42/live/339e2430-278d-11f1-a79a-77e93010d956.jpg",
      "categories": [
        "本地"
      ],
      "score": 60,
      "ago": "16小时前",
      "pub_ts": 1774359130.0,
      "hot": false
    }
  ]
}