{
  "region": "sg",
  "name": "新加坡",
  "updated_at": "2026-04-07T11:41:42.186197+00:00",
  "total": 16,
  "articles": [
    {
      "id": "ed24e1e959",
      "type": "news",
      "region": "sg",
      "source": "Straits Times",
      "lang": "en",
      "title": "2½ years’ jail for man wanted by FBI for facilitating oil supply to North Korea",
      "summary": "Kwek Kee Seng, 66, had orchestrated the supply of more than $9.5 million worth of gasoil to Pyongyang.",
      "link": "https://www.straitstimes.com/singapore/courts-crime/21-2-years-jail-for-man-wanted-by-fbi-for-facilitating-oil-supply-to-north-korea",
      "image": null,
      "categories": [
        "科技"
      ],
      "score": 70,
      "ago": "6分前",
      "pub_ts": 1775561700.0,
      "hot": false
    },
    {
      "id": "2786ff6189",
      "type": "news",
      "region": "sg",
      "source": "CNA Singapore",
      "lang": "en",
      "title": "Thailand weighing overnight petrol station closures to save fuel: PM",
      "summary": "",
      "link": "https://www.channelnewsasia.com/asia/anutin-charnvirakul-thai-pm-weighing-overnight-petrol-station-closure-save-fuel-6041161",
      "image": "https://dam.mediacorp.sg/image/upload/s--Ccr0oxJE--/fl_relative,g_south_east,l_mediacorp:cna:watermark:2023-11:afp_watermark_14112023,w_0.1/f_auto,q_auto/c_fill,g_auto,h_468,w_830/v1/mediacorp/cna/image/2026/04/07/000_a3mx44d.jpg?itok=MJ603fek",
      "categories": [
        "科技"
      ],
      "score": 70,
      "ago": "12分前",
      "pub_ts": 1775561362.0,
      "hot": false
    },
    {
      "id": "e9ff768d16",
      "type": "news",
      "region": "sg",
      "source": "CNA Singapore",
      "lang": "en",
      "title": "Former player Barton pleads not guilty to golf club attack, BBC reports",
      "summary": "",
      "link": "https://www.channelnewsasia.com/sport/former-player-barton-pleads-not-guilty-golf-club-attack-bbc-reports-6041191",
      "image": "https://dam.mediacorp.sg/image/upload/s--FbNiKVk6--/fl_relative,g_south_east,l_mediacorp:cna:watermark:2024-04:reuters_1,w_0.1/f_auto,q_auto/c_fill,g_auto,h_468,w_830/v1/one-cms/core/2026-04-07T112822Z_1_LYNXMPEM360LR_RTROPTP_3_BRITAIN-COURT-BARTON.JPG?itok=3GsOX644",
      "categories": [
        "本地"
      ],
      "score": 70,
      "ago": "13分前",
      "pub_ts": 1775561302.0,
      "hot": false
    },
    {
      "id": "43d3502e9c",
      "type": "news",
      "region": "sg",
      "source": "CNA Singapore",
      "lang": "en",
      "title": "Road tax rebates, reducing petrol duties to address rising fuel prices a blunt tool: Jeffrey Siow",
      "summary": "More than 30 Members of Parliament sought clarifications in Parliament after three ministerial statements on the impact of the conflict on Singapore.",
      "link": "https://www.channelnewsasia.com/singapore/middle-east-conflict-road-tax-rebates-energy-supply-support-workers-readiness-6041091",
      "image": "https://dam.mediacorp.sg/image/upload/s--RJKTCN9a--/c_crop,h_538,w_958,x_1,y_1/fl_relative,g_south_east,l_mediacorp:cna:watermark:2021-08:cna,w_0.1/f_auto,q_auto/c_fill,g_auto,h_468,w_830/singapore-traffic_0.jpg?itok=9bUUJ9d5",
      "categories": [
        "政治",
        "经济"
      ],
      "score": 70,
      "ago": "14分前",
      "pub_ts": 1775561236.0,
      "hot": false
    },
    {
      "id": "0116e198f3",
      "type": "news",
      "region": "sg",
      "source": "CNA Singapore",
      "lang": "en",
      "title": "One attacker dead, two injured in gunfight outside Israeli consulate in Istanbul",
      "summary": "",
      "link": "https://www.channelnewsasia.com/world/shooting-israeli-consulate-istanbul-turkiye-6041141",
      "image": "https://dam.mediacorp.sg/image/upload/s--N99W1dnX--/f_auto,q_auto/c_fill,g_auto,h_468,w_830/v1/mediacorp/cna/image/2026/04/07/gunfire_at_israel_consulate.jpg?itok=z7NCILuR",
      "categories": [
        "本地"
      ],
      "score": 70,
      "ago": "20分前",
      "pub_ts": 1775560860.0,
      "hot": false
    },
    {
      "id": "3a14d76e52",
      "type": "news",
      "region": "sg",
      "source": "CNA Singapore",
      "lang": "en",
      "title": "Former Wales captain Ramsey retires at age 35",
      "summary": "",
      "link": "https://www.channelnewsasia.com/sport/former-wales-captain-ramsey-retires-age-35-6041136",
      "image": null,
      "categories": [
        "科技"
      ],
      "score": 70,
      "ago": "31分前",
      "pub_ts": 1775560193.0,
      "hot": false
    },
    {
      "id": "37de1aec30",
      "type": "news",
      "region": "sg",
      "source": "Straits Times",
      "lang": "en",
      "title": "Drink driver whose car struck cyclist in 2022 drove again after consuming alcohol in 2024",
      "summary": "Heng Zeng An's mitigation and sentencing will take place on April 20.",
      "link": "https://www.straitstimes.com/singapore/courts-crime/drink-driver-whose-car-struck-cyclist-in-2022-drove-again-after-consuming-alcohol-in-2024",
      "image": null,
      "categories": [
        "科技"
      ],
      "score": 70,
      "ago": "46分前",
      "pub_ts": 1775559300.0,
      "hot": false
    },
    {
      "id": "7bb0012148",
      "type": "news",
      "region": "sg",
      "source": "Straits Times",
      "lang": "en",
      "title": "‘Unprecedented’ energy disruption from Middle East conflict; Govt announces support measures",
      "summary": "The conflict will impact more sectors of S'pore's economy, lead to higher electricity, food prices: DPM Gan",
      "link": "https://www.straitstimes.com/singapore/politics/unprecedented-energy-disruption-from-middle-east-conflict-govt-announces-support-measures",
      "image": null,
      "categories": [
        "经济"
      ],
      "score": 70,
      "ago": "55分前",
      "pub_ts": 1775558760.0,
      "hot": false
    },
    {
      "id": "6f3ed6760f",
      "type": "news",
      "region": "sg",
      "source": "CNA Singapore",
      "lang": "en",
      "title": "US striker Agyemang ruled out of World Cup due to injury",
      "summary": "",
      "link": "https://www.channelnewsasia.com/sport/us-striker-agyemang-ruled-out-world-cup-due-injury-6041081",
      "image": "https://dam.mediacorp.sg/image/upload/s--_Ak4nyVs--/fl_relative,g_south_east,l_mediacorp:cna:watermark:2024-04:reuters_1,w_0.1/f_auto,q_auto/c_fill,g_auto,h_468,w_830/v1/one-cms/core/2026-04-07T104118Z_1_LYNXMPEM360JL_RTROPTP_3_SOCCER-USA.JPG?itok=LTIMds1b",
      "categories": [
        "本地"
      ],
      "score": 70,
      "ago": "1小时前",
      "pub_ts": 1775558478.0,
      "hot": false
    },
    {
      "id": "e91fc330d5",
      "type": "news",
      "region": "sg",
      "source": "CNA Singapore",
      "lang": "en",
      "title": "Singapore will not negotiate for safe passage through Strait of Hormuz: Vivian Balakrishnan",
      "summary": "Foreign Affairs Minister Vivian Balakrishnan stressed that transit through such waterways is a right, not a privilege.",
      "link": "https://www.channelnewsasia.com/singapore/strait-hormuz-safe-passage-vivian-balakrishnan-6040981",
      "image": "https://dam.mediacorp.sg/image/upload/s--TiXha1Ft--/f_auto,q_auto/c_fill,g_auto,h_468,w_830/v1/mediacorp/cna/image/2026/04/07/vivian.png?itok=kMimZ84K",
      "categories": [
        "政治",
        "科技"
      ],
      "score": 70,
      "ago": "1小时前",
      "pub_ts": 1775557860.0,
      "hot": false
    },
    {
      "id": "53a205da4c",
      "type": "news",
      "region": "sg",
      "source": "CNA Singapore",
      "lang": "en",
      "title": "After milestone-rich lunar flyby, astronauts start trip home",
      "summary": "",
      "link": "https://www.channelnewsasia.com/world/artemis-ii-nasa-astronauts-trip-home-moon-flyby-6041046",
      "image": "https://dam.mediacorp.sg/image/upload/s--5wqcOJbX--/c_crop,h_360,w_640,x_0,y_47/f_auto,q_auto/c_fill,g_auto,h_468,w_830/v1/mediacorp/cna/image/2026/04/07/download_1.jpg?itok=LN0bJRYS",
      "categories": [
        "本地"
      ],
      "score": 70,
      "ago": "1小时前",
      "pub_ts": 1775557260.0,
      "hot": false
    },
    {
      "id": "dc2d6d7d25",
      "type": "news",
      "region": "sg",
      "source": "Straits Times",
      "lang": "en",
      "title": "How can Singapore beat the heat and high electricity prices without aircon?",
      "summary": "Improving people’s ability to withstand hotter weather is one part of Singapore’s adaptation plan.",
      "link": "https://www.straitstimes.com/singapore/environment/how-can-singapore-beat-the-heat-and-high-electricity-prices-without-aircon",
      "image": null,
      "categories": [
        "天气",
        "科技"
      ],
      "score": 70,
      "ago": "1小时前",
      "pub_ts": 1775556000.0,
      "hot": false
    },
    {
      "id": "f4ef0f0ddb",
      "type": "news",
      "region": "sg",
      "source": "Straits Times",
      "lang": "en",
      "title": "11½ years’ jail for man with three-decade criminal history after he attacked stranger with sickle",
      "summary": "Lau Kwee Yong was also charged over using a flower pot to hit a man’s head and for attempting to grab a policewoman.",
      "link": "https://www.straitstimes.com/singapore/courts-crime/111-2-years-jail-for-man-with-three-decade-criminal-history-after-he-attacked-stranger-with-sickle",
      "image": null,
      "categories": [
        "科技"
      ],
      "score": 65,
      "ago": "2小时前",
      "pub_ts": 1775553300.0,
      "hot": false
    },
    {
      "id": "26fe4c262c",
      "type": "news",
      "region": "sg",
      "source": "Straits Times",
      "lang": "en",
      "title": "ComfortDelGro rolls out invitational rides on its autonomous shuttle service in Punggol",
      "summary": "Later on, the public will be able to book these rides using the transport operator’s app.",
      "link": "https://www.straitstimes.com/singapore/transport/comfortdelgro-rolls-out-invitational-rides-on-its-autonomous-shuttle-service-in-punggol",
      "image": null,
      "categories": [
        "本地"
      ],
      "score": 65,
      "ago": "2小时前",
      "pub_ts": 1775552400.0,
      "hot": false
    },
    {
      "id": "6148a993fc",
      "type": "news",
      "region": "sg",
      "source": "Straits Times",
      "lang": "en",
      "title": "More than 84,500 people have signed advance medical directive in Singapore to date",
      "summary": "Meanwhile, about 404,000 Singapore citizens have made an LPA since the scheme started in 2010.",
      "link": "https://www.straitstimes.com/singapore/politics/more-than-84500-people-have-signed-advance-medical-directive-to-date",
      "image": null,
      "categories": [
        "本地"
      ],
      "score": 65,
      "ago": "2小时前",
      "pub_ts": 1775552340.0,
      "hot": false
    },
    {
      "id": "94d6564653",
      "type": "news",
      "region": "sg",
      "source": "Straits Times",
      "lang": "en",
      "title": "S’pore to up fuel reserves; electricity prices will rise sharply if conflict is prolonged: Shanmugam",
      "summary": "The Republic has sufficient buffers and contingency plans in place, the minister said.",
      "link": "https://www.straitstimes.com/singapore/politics/spore-to-up-fuel-reserves-electricity-prices-will-rise-sharply-if-conflict-is-prolonged-shanmugam",
      "image": null,
      "categories": [
        "政治",
        "科技"
      ],
      "score": 65,
      "ago": "3小时前",
      "pub_ts": 1775548035.0,
      "hot": false
    }
  ]
}