{
  "region": "kr",
  "name": "韩国",
  "updated_at": "2026-05-21T16:00:50.786294+00:00",
  "total": 8,
  "articles": [
    {
      "id": "1d8da2c542",
      "type": "news",
      "region": "kr",
      "source": "Yonhap News",
      "lang": "en",
      "title": "Slump in rearview mirror, young Heroes catcher having fun amid power surge",
      "summary": "SEOUL, May 21 (Yonhap) -- There were nights earlier this season when Kiwoom Hero...",
      "link": "https://en.yna.co.kr/view/AEN20260521012400315",
      "image": "https://img.yna.co.kr/etc/inner/EN/2026/05/21/AEN20260521012400315_01_i_P2.jpg",
      "categories": [
        "本地"
      ],
      "score": 65,
      "ago": "2小时前",
      "pub_ts": 1779369962.0,
      "hot": false
    },
    {
      "id": "6459db4bd5",
      "type": "news",
      "region": "kr",
      "source": "Yonhap News",
      "lang": "en",
      "title": "(LEAD) Heroes earn season-high 4th straight win with sweep of Landers",
      "summary": "SEOUL, May 21 (Yonhap) -- This was a memorable day for the Kiwoom Heroes battery...",
      "link": "https://en.yna.co.kr/view/AEN20260521012251315",
      "image": "https://img.yna.co.kr/etc/inner/EN/2026/05/21/AEN20260521012251315_03_i_P2.jpg",
      "categories": [
        "科技"
      ],
      "score": 65,
      "ago": "2小时前",
      "pub_ts": 1779369466.0,
      "hot": false
    },
    {
      "id": "a06a0de119",
      "type": "news",
      "region": "kr",
      "source": "Yonhap News",
      "lang": "en",
      "title": "(LEAD) Court rejects arrest warrant for ex-KTV chief over alleged insurrection propaganda",
      "summary": "SEOUL, May 21 (Yonhap) -- A Seoul court on Thursday denied an arrest warrant for...",
      "link": "https://en.yna.co.kr/view/AEN20260521004751315",
      "image": "https://img.yna.co.kr/etc/inner/EN/2026/05/21/AEN20260521004751315_02_i_P2.jpg",
      "categories": [
        "本地"
      ],
      "score": 65,
      "ago": "3小时前",
      "pub_ts": 1779367826.0,
      "hot": false
    },
    {
      "id": "369e7c33f6",
      "type": "news",
      "region": "kr",
      "source": "Yonhap News",
      "lang": "en",
      "title": "KBO tops 4 mln fans in fewest games",
      "summary": "SEOUL, May 21 (Yonhap) -- The South Korean baseball league reached 4 million fan...",
      "link": "https://en.yna.co.kr/view/AEN20260521012300315",
      "image": "https://img.yna.co.kr/photo/yna/YH/2026/05/21/PYH2026052126720001300_P2.jpg",
      "categories": [
        "本地"
      ],
      "score": 65,
      "ago": "3小时前",
      "pub_ts": 1779367551.0,
      "hot": false
    },
    {
      "id": "b993cdad51",
      "type": "news",
      "region": "kr",
      "source": "Yonhap News",
      "lang": "en",
      "title": "Heroes earn season-high 4th straight win with sweep of Landers",
      "summary": "SEOUL, May 21 (Yonhap) -- This was a memorable day for the Kiwoom Heroes battery...",
      "link": "https://en.yna.co.kr/view/AEN20260521012200315",
      "image": "https://img.yna.co.kr/etc/inner/EN/2026/05/21/AEN20260521012200315_03_i_P2.jpg",
      "categories": [
        "科技"
      ],
      "score": 65,
      "ago": "3小时前",
      "pub_ts": 1779367278.0,
      "hot": false
    },
    {
      "id": "02f3b69813",
      "type": "news",
      "region": "kr",
      "source": "Yonhap News",
      "lang": "en",
      "title": "(LEAD) Bears extend deal with temporary injury replacement Benjamin",
      "summary": "SEOUL, May 21 (Yonhap) -- The Doosan Bears announced Thursday they have extended...",
      "link": "https://en.yna.co.kr/view/AEN20260521012051315",
      "image": "https://img.yna.co.kr/photo/yna/YH/2026/04/21/PYH2026042118730005100_P2.jpg",
      "categories": [
        "本地"
      ],
      "score": 65,
      "ago": "3小时前",
      "pub_ts": 1779365164.0,
      "hot": false
    },
    {
      "id": "bcb3c54b5b",
      "type": "news",
      "region": "kr",
      "source": "Yonhap News",
      "lang": "en",
      "title": "Korea-U.S. Alliance Foundation holds joint memorial to commemorate Korean War veterans in Paju",
      "summary": "SEOUL, May 21 (Yonhap) -- The Korea-U.S. Alliance Foundation on Thursday held a ...",
      "link": "https://en.yna.co.kr/view/AEN20260521012100315",
      "image": "https://img.yna.co.kr/etc/inner/EN/2026/05/21/AEN20260521012100315_01_i_P2.jpg",
      "categories": [
        "本地"
      ],
      "score": 65,
      "ago": "5小时前",
      "pub_ts": 1779359133.0,
      "hot": false
    },
    {
      "id": "c486dc89ab",
      "type": "news",
      "region": "kr",
      "source": "Yonhap News",
      "lang": "en",
      "title": "Bears extend deal with temporary injury replacement Benjamin",
      "summary": "SEOUL, May 21 (Yonhap) -- The Doosan Bears announced Thursday they have extended...",
      "link": "https://en.yna.co.kr/view/AEN20260521012000315",
      "image": "https://img.yna.co.kr/photo/yna/YH/2026/04/21/PYH2026042118730005100_P2.jpg",
      "categories": [
        "本地"
      ],
      "score": 65,
      "ago": "5小时前",
      "pub_ts": 1779358944.0,
      "hot": false
    }
  ]
}